narm2_SBU/__init__.py
narm2_SBU/module1.py
narm2_SBU/module2.py
narm2_SBU-1.0.dist-info/METADATA
narm2_SBU-1.0.dist-info/WHEEL
narm2_SBU-1.0.dist-info/top_level.txt
narm2_SBU-1.0.dist-info/RECORD
