Metadata-Version: 2.1
Name: narm2-SBU
Version: 1.0
Summary: testing for narm 2
